xparse_client/__init__.py
xparse_client/pipeline/__init__.py
xparse_client/pipeline/config.py
xparse_client/pipeline/destinations.py
xparse_client/pipeline/pipeline.py
xparse_client/pipeline/sources.py
xparse_client-0.2.20.dist-info/licenses/LICENSE
xparse_client-0.2.20.dist-info/METADATA
xparse_client-0.2.20.dist-info/WHEEL
xparse_client-0.2.20.dist-info/top_level.txt
xparse_client-0.2.20.dist-info/RECORD
