Metadata-Version: 2.4
Name: xparse-client
Version: 0.2.20
Summary: 面向Agent和RAG的新一代文档处理 AI Infra
License-Expression: MIT
Project-URL: Homepage, https://gitlab.intsig.net/xparse1/xparse-pipeline
Project-URL: Repository, https://gitlab.intsig.net/xparse1/xparse-pipeline
Keywords: xparse,pipeline,rag
Requires-Python: >=3.8
License-File: LICENSE
Requires-Dist: boto3
Requires-Dist: pymilvus
Requires-Dist: milvus-lite; sys_platform != "win32"
Requires-Dist: requests
Requires-Dist: pysmb
Requires-Dist: qdrant-client
Dynamic: license-file
